tree_sitter_julia/binding.c
tree_sitter_julia/__init__.pyi
tree_sitter_julia/py.typed
tree_sitter_julia/_binding.abi3.so
tree_sitter_julia/__init__.py
tree_sitter_julia-0.23.0.dist-info/RECORD
tree_sitter_julia-0.23.0.dist-info/WHEEL
tree_sitter_julia-0.23.0.dist-info/LICENSE
tree_sitter_julia-0.23.0.dist-info/top_level.txt
tree_sitter_julia-0.23.0.dist-info/METADATA
